aiotr/__init__.py
aiotr/client.py
aiotr/exception.py
aiotr/py.typed
aiotr/typing.py
aiotr/utils.py
aiotr-0.1.2.dist-info/LICENSE
aiotr-0.1.2.dist-info/METADATA
aiotr-0.1.2.dist-info/WHEEL
aiotr-0.1.2.dist-info/top_level.txt
aiotr-0.1.2.dist-info/RECORD
